fabric/__init__.py
fabric/analysis.py
fabric/common_args.py
fabric/gene_score_dist.py
fabric/gene_testing.py
fabric/util.py
fabric/vcf_processing.py
fabric_genetics-1.2.0.data/scripts/fabric
fabric_genetics-1.2.0.data/scripts/vcf_to_csv
fabric_genetics-1.2.0.dist-info/METADATA
fabric_genetics-1.2.0.dist-info/WHEEL
fabric_genetics-1.2.0.dist-info/top_level.txt
fabric_genetics-1.2.0.dist-info/RECORD
